LICENSE.md
fritzexporter/__init__.py
fritzexporter/__main__.py
fritzexporter/action_blacklists.py
fritzexporter/config/__init__.py
fritzexporter/config/config.py
fritzexporter/config/exceptions.py
fritzexporter/data_donation.py
fritzexporter/exceptions.py
fritzexporter/fritz_aha.py
fritzexporter/fritzcapabilities.py
fritzexporter/fritzdevice.py
fritz_exporter-2.6.0.dist-info/LICENSE.md
fritz_exporter-2.6.0.dist-info/METADATA
fritz_exporter-2.6.0.dist-info/WHEEL
fritz_exporter-2.6.0.dist-info/entry_points.txt
fritz_exporter-2.6.0.dist-info/RECORD
