Metadata-Version: 2.1
Name: fritz-exporter
Version: 2.6.0
Summary: Prometheus exporter for AVM Fritz! Devices
Home-page: https://github.com/pdreker/fritz_exporter
License: Apache 2.0
Keywords: prometheus,fritz,router,grafana
Author: Patrick Dreker
Author-email: patrick@dreker.de
Requires-Python: >=3.11,<4.0
Classifier: Development Status :: 6 - Mature
Classifier: Environment :: Console
Classifier: License :: OSI Approved :: Apache Software License
Classifier: License :: Other/Proprietary License
Classifier: Operating System :: OS Independent
Classifier: Programming Language :: Python :: 3
Classifier: Programming Language :: Python :: 3.11
Classifier: Programming Language :: Python :: 3.12
Classifier: Topic :: System :: Monitoring
Requires-Dist: attrs (>=22.2,<26.0)
Requires-Dist: defusedxml (>=0.7.1,<0.8.0)
Requires-Dist: fritzconnection (>=1.0.0)
Requires-Dist: prometheus-client (>=0.6.0)
Requires-Dist: pyyaml
Requires-Dist: requests
Project-URL: Documentation, https://fritz-exporter.readthedocs.io
Project-URL: Repository, https://github.com/pdreker/fritz_exporter
